Metadata-Version: 1.0
Name: core-elasticsearch-app
Version: 2.5.0
Summary: Elasticsearch utils for the curator core project
Home-page: https://github.com/usnistgov/core_elasticsearch_app
Author: NIST IT Lab
Author-email: itl_inquiries@nist.gov
License: UNKNOWN
Platform: UNKNOWN
